[
  {
    "name": "Funke Akindele",
    "country": "NG",
    "tmdb_id": 1177552,
    "profile_path": "/cjV3OUS14Mkbg6GILTZBSO2ovtD.jpg",
    "tmdb_known_for": [
      "Far from Home",
      "Chief Daddy 2: Going for Broke",
      "House of Ga'a"
    ]
  },
  {
    "name": "Niyi Akinmolayan",
    "country": "NG",
    "tmdb_id": 1682188,
    "profile_path": "/5x93lkT8lQ9FX0dDGzWaxBQRFQv.jpg",
    "tmdb_known_for": [
      "Chief Daddy 2: Going for Broke",
      "Lisabi: The Uprising",
      "The Set Up"
    ]
  },
  {
    "name": "Kemi Adetiba",
    "country": "NG",
    "tmdb_id": 1668703,
    "profile_path": "/tiqrAogVqMTu3TC6lqIQhfTKseS.jpg",
    "tmdb_known_for": [
      "The Wedding Party",
      "To Kill a Monkey",
      "King of Boys"
    ]
  },
  {
    "name": "Kayode Kasum",
    "country": "NG",
    "tmdb_id": 2504534,
    "profile_path": null,
    "tmdb_known_for": [
      "Sugar Rush",
      "Quam's Money",
      "Something Like Gold"
    ]
  },
  {
    "name": "Biodun Stephen",
    "country": "NG",
    "tmdb_id": 1826789,
    "profile_path": "/2LnLSaH8gMPFn0jojcq9dg30wnC.jpg",
    "tmdb_known_for": [
      "To Freedom",
      "Big Love",
      "Breaded Life"
    ]
  },
  {
    "name": "Moses Inwang",
    "country": "NG",
    "tmdb_id": 1484323,
    "profile_path": null,
    "tmdb_known_for": [
      "Blood Vessel",
      "Merry Men 2: Another Mission",
      "American Driver"
    ]
  },
  {
    "name": "Tope Adebayo",
    "country": "NG",
    "tmdb_id": 3649935,
    "profile_path": null,
    "tmdb_known_for": [
      "Jagun Jagun",
      "Ori Rebirth",
      "Abánisétè: The Ancestor"
    ]
  },
  {
    "name": "Robert Peters",
    "country": "NG",
    "tmdb_id": 2918605,
    "profile_path": null,
    "tmdb_known_for": [
      "Special Jollof"
    ]
  },
  {
    "name": "Loukman Ali",
    "country": "NG",
    "tmdb_id": 2662546,
    "profile_path": "/bn8Xx46lUhtw0Zdt7tnc10NMsTH.jpg",
    "tmdb_known_for": [
      "The Girl in the Yellow Jumper",
      "African Folktales Reimagined",
      "Brotherhood"
    ]
  },
  {
    "name": "Kunle Afolayan",
    "country": "NG",
    "tmdb_id": 1428024,
    "profile_path": "/1pDeg5kVulTBLqrJuw2LkvfDJ5i.jpg",
    "tmdb_known_for": [
      "Citation",
      "A Naija Christmas",
      "Aníkúlápó"
    ]
  },
  {
    "name": "Tunde Kelani",
    "country": "NG",
    "tmdb_id": 1176072,
    "profile_path": "/ySDmbM5bzU4fG4UOBiIwdNsvkL8.jpg",
    "tmdb_known_for": [
      "Agogo Èèwò",
      "Ayinla",
      "Cordelia"
    ]
  },
  {
    "name": "Izu Ojukwu",
    "country": "NG",
    "tmdb_id": 1668693,
    "profile_path": null,
    "tmdb_known_for": [
      "Amina",
      "'76",
      "Across the Niger"
    ]
  },
  {
    "name": "Mildred Okwo",
    "country": "NG",
    "tmdb_id": 1700664,
    "profile_path": null,
    "tmdb_known_for": [
      "La Femme Anjola",
      "The Meeting",
      "30 Days"
    ]
  },
  {
    "name": "C.J. Obasi",
    "country": "NG",
    "tmdb_id": 2111004,
    "profile_path": "/3e1wnJdscM33ILavuEGbLh4rh6E.jpg",
    "tmdb_known_for": [
      "Mami Wata",
      "Juju Stories",
      "Hello, Rain"
    ]
  },
  {
    "name": "Newton Aduaka",
    "country": "NG",
    "tmdb_id": 88693,
    "profile_path": null,
    "tmdb_known_for": [
      "Ezra",
      "Rage",
      "On the Edge"
    ]
  },
  {
    "name": "Lancelot Oduwa Imasuen",
    "country": "NG",
    "tmdb_id": 1174073,
    "profile_path": null,
    "tmdb_known_for": [
      "ABCs of Death 2",
      "Invasion 1897",
      "A Piece of Flesh"
    ]
  },
  {
    "name": "Jeta Amata",
    "country": "NG",
    "tmdb_id": 968998,
    "profile_path": "/ldDF4fLswp1GQs6LJG4VXIcmSQF.jpg",
    "tmdb_known_for": [
      "Black November",
      "Inalé",
      "The Amazing Grace"
    ]
  },
  {
    "name": "Ramsey Nouah",
    "country": "NG",
    "tmdb_id": 3645050,
    "profile_path": "/yHA9WfTrv70pQL1aWLegLFz7U6I.jpg",
    "tmdb_known_for": [
      "Levi",
      "A Country Called Ghana",
      "The Black Soul 2"
    ]
  },
  {
    "name": "Femi Odugbemi",
    "country": "NG",
    "tmdb_id": 1693760,
    "profile_path": "/A7oJaJtU7qT6nQ4aMd7rHHrngPu.jpg",
    "tmdb_known_for": [
      "Maroko",
      "Gidi Blues",
      "Makoko: Futures Afloat"
    ]
  },
  {
    "name": "Chico Ejiro",
    "country": "NG",
    "tmdb_id": 1180818,
    "profile_path": null,
    "tmdb_known_for": [
      "Fools",
      "Scores to Settle",
      "Blood Money"
    ]
  },
  {
    "name": "Toka McBaror",
    "country": "NG",
    "tmdb_id": 2053285,
    "profile_path": "/8x9isnUjvsLcwJGemWd8dPLUN0h.jpg",
    "tmdb_known_for": [
      "Merry Men: The Real Yoruba Demons",
      "Ikogosi",
      "The Island"
    ]
  },
  {
    "name": "Teco Benson",
    "country": "NG",
    "tmdb_id": 1332093,
    "profile_path": null,
    "tmdb_known_for": [
      "End of the Wicked",
      "Holy Crime",
      "Mission to Nowhere"
    ]
  },
  {
    "name": "Andy Amenechi",
    "country": "NG",
    "tmdb_id": 1352015,
    "profile_path": null,
    "tmdb_known_for": [
      "Sympathy",
      "Passionate Appeal",
      "Golden Moon 2"
    ]
  },
  {
    "name": "Jean-Pierre Bekolo",
    "country": "CM",
    "tmdb_id": 1177451,
    "profile_path": "/h6Unv3mPSYlpMc1kITz0Xx59UMg.jpg",
    "tmdb_known_for": [
      "The Bloodiest",
      "Aristotle's Plot",
      "Quartier Mozart"
    ]
  },
  {
    "name": "Bassek ba Kobhio",
    "country": "CM",
    "tmdb_id": 1324312,
    "profile_path": "/sE9muyRdiDAWwpRYicifzytuNje.jpg",
    "tmdb_known_for": [
      "Chocolat",
      "The Great White of Lambarene",
      "Sango Malo"
    ]
  },
  {
    "name": "Rosine Mbakam",
    "country": "CM",
    "tmdb_id": 1285133,
    "profile_path": "/iSdTvnD9iZOriuLAQ8suf2K4itN.jpg",
    "tmdb_known_for": [
      "Chez Jolie Coiffure",
      "Mambar Pierrette",
      "Delphine’s Prayers"
    ]
  },
  {
    "name": "Nkanya Nkwai",
    "country": "CM",
    "tmdb_id": 2812442,
    "profile_path": null,
    "tmdb_known_for": [
      "Saving Mbango"
    ]
  },
  {
    "name": "Samantha Biffot",
    "country": "CM",
    "tmdb_id": 1890484,
    "profile_path": null,
    "tmdb_known_for": [
      "The African Who Wanted to Fly"
    ]
  },
  {
    "name": "Max Ngassa",
    "country": "CM",
    "tmdb_id": 4523147,
    "profile_path": null,
    "tmdb_known_for": [
      "Kuvah - Legend of The Sea"
    ]
  },
  {
    "name": "Frank Thierry Lea Malle",
    "country": "CM",
    "tmdb_id": 3605395,
    "profile_path": null,
    "tmdb_known_for": [
      "The Agreement",
      "Innocent(e)",
      "Agents Un Peu Trop Secrets"
    ]
  },
  {
    "name": "Enah Johnscott",
    "country": "CM",
    "tmdb_id": 2930101,
    "profile_path": null,
    "tmdb_known_for": [
      "The Fisherman's Diary",
      "Half Heaven"
    ]
  },
  {
    "name": "Daniel Kamwa",
    "country": "CM",
    "tmdb_id": 1323998,
    "profile_path": "/d0tmExdErlO03KLRcrz1iz0230j.jpg",
    "tmdb_known_for": [
      "Turtle",
      "Our Daughter",
      "Boubou cravate"
    ]
  },
  {
    "name": "Jean-Marie Téno",
    "country": "CM",
    "tmdb_id": 1168265,
    "profile_path": "/AHjaq4F2wksyv43sjOpiQSN5Ro.jpg",
    "tmdb_known_for": [
      "Africa, I Will Fleece You",
      "Sacred Places",
      "Chef!"
    ]
  },
  {
    "name": "Joséphine Ndagnou",
    "country": "CM",
    "tmdb_id": 1809392,
    "profile_path": "/7bD2ooigDO1FzmV5QIAJR5s8Mtx.jpg",
    "tmdb_known_for": [
      "The Bloodiest",
      "Le retraité"
    ]
  },
  {
    "name": "Ebénézer Kepombia",
    "country": "CM",
    "tmdb_id": 3484104,
    "profile_path": null,
    "tmdb_known_for": [
      "Madame… Monsieur",
      "Habiba",
      "Otages D’amour"
    ]
  },
  {
    "name": "Kang Quintus",
    "country": "CM",
    "tmdb_id": 2930100,
    "profile_path": "/2Zj6uW21cFCZKKaEyCZTfhwyu8F.jpg",
    "tmdb_known_for": [
      "The Fisherman's Diary",
      "Nganù"
    ]
  },
  {
    "name": "Shirley Frimpong-Manso",
    "country": "GH",
    "tmdb_id": 1023504,
    "profile_path": null,
    "tmdb_known_for": [
      "Potato Potahto",
      "Scorned",
      "Grey Dawn"
    ]
  },
  {
    "name": "Kwaw Ansah",
    "country": "GH",
    "tmdb_id": 1323284,
    "profile_path": null,
    "tmdb_known_for": [
      "Heritage Africa",
      "Love Brewed in the African Pot",
      "Harvest at 17"
    ]
  },
  {
    "name": "Blitz Bazawule",
    "country": "GH",
    "tmdb_id": 1507725,
    "profile_path": "/kxkbGIqHic2KCCBZBQ3isrkv7fG.jpg",
    "tmdb_known_for": [
      "The Color Purple",
      "Black Is King",
      "The Burial of Kojo"
    ]
  },
  {
    "name": "Leila Djansi",
    "country": "GH",
    "tmdb_id": 1108581,
    "profile_path": "/6nR0NrARMojVbFpGm3J5t7yaTSn.jpg",
    "tmdb_known_for": [
      "And Then There Was You",
      "Where Children Play",
      "Like Cotton Twines"
    ]
  },
  {
    "name": "Peter Sedufia",
    "country": "GH",
    "tmdb_id": 2263954,
    "profile_path": null,
    "tmdb_known_for": [
      "Keteke",
      "Aloevera",
      "Sidechic Gang"
    ]
  },
  {
    "name": "King Ampaw",
    "country": "GH",
    "tmdb_id": 69686,
    "profile_path": "/e3ucIiA2KjmmnvrpySSSkqjz5s5.jpg",
    "tmdb_known_for": [
      "No Time to Die",
      "Kukurantumi",
      "Nana Akoto"
    ]
  },
  {
    "name": "Frank Rajah Arase",
    "country": "GH",
    "tmdb_id": 1466819,
    "profile_path": null,
    "tmdb_known_for": [
      "The Bargain",
      "Iyore",
      "Somewhere in Africa"
    ]
  },
  {
    "name": "Socrate Safo",
    "country": "GH",
    "tmdb_id": 5671759,
    "profile_path": null,
    "tmdb_known_for": [
      "Sakawa Boys"
    ]
  },
  {
    "name": "Pascal Amanfo",
    "country": "GH",
    "tmdb_id": 1484318,
    "profile_path": null,
    "tmdb_known_for": [
      "Agony of the Christ",
      "If God be for us",
      "Royal Messengers"
    ]
  },
  {
    "name": "Samuel K. Nkansah",
    "country": "GH",
    "tmdb_id": 1435851,
    "profile_path": "/7Y1KQpbtToWTBP9FYj5i8pj1kef.jpg",
    "tmdb_known_for": [
      "African Kung-Fu Nazis",
      "2016: Part 1",
      "2016: Part 2"
    ]
  },
  {
    "name": "Nii Kwate Owoo",
    "country": "GH",
    "tmdb_id": 1745519,
    "profile_path": null,
    "tmdb_known_for": [
      "You Hide Me",
      "Ama",
      "Ouaga"
    ]
  },
  {
    "name": "Akosua Adoma Owusu",
    "country": "GH",
    "tmdb_id": 1250333,
    "profile_path": "/7aD3NcIV3uWxfkbaSgAAeQPuFUV.jpg",
    "tmdb_known_for": [
      "White Afro",
      "Kwaku Ananse",
      "Reluctantly Queer"
    ]
  },
  {
    "name": "Ivan Quashigah",
    "country": "GH",
    "tmdb_id": 2494969,
    "profile_path": null,
    "tmdb_known_for": [
      "YOLO"
    ]
  },
  {
    "name": "Abdul Salam Mumuni",
    "country": "GH",
    "tmdb_id": 4504364,
    "profile_path": null,
    "tmdb_known_for": [
      "Beyonce: The President's Daughter",
      "The Return of Beyonce 2"
    ]
  },
  {
    "name": "Darrell Roodt",
    "country": "ZA",
    "tmdb_id": 16730,
    "profile_path": "/iJ0oqs5Il1B6hEV2A1FLmTYeMXz.jpg",
    "tmdb_known_for": [
      "Prey",
      "Lake Placid: Legacy",
      "Dracula 3000"
    ]
  },
  {
    "name": "Gavin Hood",
    "country": "ZA",
    "tmdb_id": 13079,
    "profile_path": "/2y2eX4m7qsDgbo51XAK6TE6dJon.jpg",
    "tmdb_known_for": [
      "X-Men Origins: Wolverine",
      "Ender's Game",
      "Eye in the Sky"
    ]
  },
  {
    "name": "Oliver Schmitz",
    "country": "ZA",
    "tmdb_id": 21683,
    "profile_path": null,
    "tmdb_known_for": [
      "Paris Je T'aime",
      "Türkisch für Anfänger",
      "Shepherds and Butchers"
    ]
  },
  {
    "name": "Jahmil X.T. Qubeka",
    "country": "ZA",
    "tmdb_id": 1184467,
    "profile_path": "/z5cOfARli9CGkfYgcLAAx1k1lGf.jpg",
    "tmdb_known_for": [
      "The Queenstown Kings",
      "Of Good Report",
      "Sew the Winter to My Skin"
    ]
  },
  {
    "name": "John Kani",
    "country": "ZA",
    "tmdb_id": 51878,
    "profile_path": "/g7tqg3q128a5O2qXMCwVnXsow9I.jpg",
    "tmdb_known_for": [
      "The Lion King",
      "Black Panther",
      "Captain America: Civil War"
    ]
  },
  {
    "name": "Sara Blecher",
    "country": "ZA",
    "tmdb_id": 1070319,
    "profile_path": null,
    "tmdb_known_for": [
      "Ayanda",
      "Dis ek, Anna",
      "Otelo Burning"
    ]
  },
  {
    "name": "Katleho Ramaphakela",
    "country": "ZA",
    "tmdb_id": 2726061,
    "profile_path": "/fZVaFsEjGZapMofluPi6HFLnSKm.jpg",
    "tmdb_known_for": [
      "Miseducation",
      "Lobola Man",
      "Bedford Wives"
    ]
  },
  {
    "name": "Akin Omotoso",
    "country": "ZA",
    "tmdb_id": 37092,
    "profile_path": "/49IQy9bmSvUfvAaIsjqIgEogWHX.jpg",
    "tmdb_known_for": [
      "Rise",
      "Marked",
      "Vaya"
    ]
  },
  {
    "name": "Madoda Ncayiyana",
    "country": "ZA",
    "tmdb_id": 1876760,
    "profile_path": null,
    "tmdb_known_for": [
      "My Secret Sky"
    ]
  },
  {
    "name": "Ramadan Suleman",
    "country": "ZA",
    "tmdb_id": 1145510,
    "profile_path": null,
    "tmdb_known_for": [
      "Fools",
      "Zulu Love Letter",
      "66 Pim Street"
    ]
  },
  {
    "name": "Ian Gabriel",
    "country": "ZA",
    "tmdb_id": 4490023,
    "profile_path": null,
    "tmdb_known_for": [
      "A Very Good Girl"
    ]
  },
  {
    "name": "Jenna Bass",
    "country": "ZA",
    "tmdb_id": 1406229,
    "profile_path": "/wA4k94JfXMB1yuQlBLaDClbufNj.jpg",
    "tmdb_known_for": [
      "Flatland",
      "Good Madam",
      "High Fantasy"
    ]
  },
  {
    "name": "Mandla Dube",
    "country": "ZA",
    "tmdb_id": 1785761,
    "profile_path": "/eoUSyYMtpo3Bp5vZ8llvmStlpDp.jpg",
    "tmdb_known_for": [
      "Heart of the Hunter",
      "Kalushi: The Story of Solomon Mahlangu",
      "Razorman"
    ]
  },
  {
    "name": "Norman Maake",
    "country": "ZA",
    "tmdb_id": 1571907,
    "profile_path": null,
    "tmdb_known_for": [
      "Love Lives Here",
      "Piet's Sake",
      "Inkabi"
    ]
  },
  {
    "name": "Donald Molosi",
    "country": "ZA",
    "tmdb_id": 1875039,
    "profile_path": "/47oy3A4H0fjWp3KsDJ7fJmBpQnU.jpg",
    "tmdb_known_for": [
      "A United Kingdom",
      "2064",
      "Our Flowers"
    ]
  },
  {
    "name": "Ousmane Sembène",
    "country": "SN",
    "tmdb_id": 557134,
    "profile_path": "/v5QkPWoui6zLgD8ROo8VfjFum6l.jpg",
    "tmdb_known_for": [
      "Black Girl",
      "Moolaadé",
      "The Wagoner"
    ]
  },
  {
    "name": "Souleymane Cissé",
    "country": "ML",
    "tmdb_id": 1075658,
    "profile_path": "/3I5mPRK20GW1Qp54BmyOmWX0xAK.jpg",
    "tmdb_known_for": [
      "Yeelen",
      "The Wind",
      "Work"
    ]
  },
  {
    "name": "Djibril Diop Mambéty",
    "country": "SN",
    "tmdb_id": 1079380,
    "profile_path": "/qP0a19xyKBoAY22ZsnJJy9Okfm6.jpg",
    "tmdb_known_for": [
      "Touki Bouki",
      "Hyenas",
      "The Little Girl Who Sold the Sun"
    ]
  },
  {
    "name": "Abderrahmane Sissako",
    "country": "MR",
    "tmdb_id": 118772,
    "profile_path": "/lQew5sGuT5Tni75EuFBnG3FjZ6n.jpg",
    "tmdb_known_for": [
      "Timbuktu",
      "Black Tea",
      "Bamako"
    ]
  },
  {
    "name": "Mahamat-Saleh Haroun",
    "country": "TD",
    "tmdb_id": 226553,
    "profile_path": "/osOIYASF3OmROpYwgoM4G0fk0tv.jpg",
    "tmdb_known_for": [
      "Lingui, the Sacred Bonds",
      "A Screaming Man",
      "A Season in France"
    ]
  },
  {
    "name": "Mati Diop",
    "country": "SN",
    "tmdb_id": 136168,
    "profile_path": "/3p8euc4PO9Yo9RR0PjaADsN9R6V.jpg",
    "tmdb_known_for": [
      "Atlantics",
      "Dahomey",
      "Atlantiques"
    ]
  },
  {
    "name": "Ramata-Toulaye Sy",
    "country": "SN",
    "tmdb_id": 3211417,
    "profile_path": "/ghGmZ0ScjfquHujJOnB2nhQYHlo.jpg",
    "tmdb_known_for": [
      "Banel & Adama",
      "Astel",
      "La Ballade de Saturne"
    ]
  },
  {
    "name": "Oumarou Ganda",
    "country": "NE",
    "tmdb_id": 238963,
    "profile_path": "/51dpcOPWYtGK973i7wuEnto77nB.jpg",
    "tmdb_known_for": [
      "The Polygamous Wazzou",
      "Cabascabo",
      "Saitane"
    ]
  },
  {
    "name": "Cheik Doukouré",
    "country": "GN",
    "tmdb_id": 230469,
    "profile_path": null,
    "tmdb_known_for": [
      "Little Indian, Big City",
      "The Professional",
      "My New Partner"
    ]
  },
  {
    "name": "Mohamed Camara",
    "country": "GN",
    "tmdb_id": 1177676,
    "profile_path": null,
    "tmdb_known_for": [
      "Destiny",
      "Denko",
      "Neuf Mois"
    ]
  },
  {
    "name": "Fadika Kramo-Lanciné",
    "country": "CI",
    "tmdb_id": 1324316,
    "profile_path": null,
    "tmdb_known_for": [
      "Wariko, le gros lot",
      "Djeli, a Modern Tale"
    ]
  },
  {
    "name": "Roger Gnoan M'Bala",
    "country": "CI",
    "tmdb_id": 1046585,
    "profile_path": "/jzXYfUcBcFK7BnFfXPykbabAmdy.jpg",
    "tmdb_known_for": [
      "Adanggaman",
      "In the Name of Christ",
      "Ablakon"
    ]
  },
  {
    "name": "Alex Ogou",
    "country": "CI",
    "tmdb_id": 3723868,
    "profile_path": null,
    "tmdb_known_for": [
      "Eki",
      "Invisibles",
      "Ô Batanga"
    ]
  },
  {
    "name": "Djo Tunda Wa Munga",
    "country": "CD",
    "tmdb_id": 238273,
    "profile_path": null,
    "tmdb_known_for": [
      "Viva Riva!",
      "State of Mind: Healing Trauma",
      "Papy"
    ]
  },
  {
    "name": "Balufu Bakupa-Kanyinda",
    "country": "CD",
    "tmdb_id": 1314871,
    "profile_path": null,
    "tmdb_known_for": [
      "Juju Factory",
      "Thomas Sankara",
      "Watt"
    ]
  },
  {
    "name": "Youssef Chahine",
    "country": "EG",
    "tmdb_id": 20023,
    "profile_path": "/eISYmf4YgY39B6ss0jbwwi2gJhz.jpg",
    "tmdb_known_for": [
      "To Each His Own Cinema",
      "Cairo Station",
      "September 11"
    ]
  },
  {
    "name": "Merzak Allouache",
    "country": "DZ",
    "tmdb_id": 82307,
    "profile_path": "/mUCtwUBJsg0nn3DXVpQeJ5UHfeF.jpg",
    "tmdb_known_for": [
      "Chouchou",
      "Lumière & Company",
      "Salut cousin !"
    ]
  },
  {
    "name": "Nabil Ayouch",
    "country": "MA",
    "tmdb_id": 285104,
    "profile_path": "/n7t19GtMJVErQ4SaSKaptVRhPnH.jpg",
    "tmdb_known_for": [
      "Much Loved",
      "Horses of God",
      "Ali Zaoua: Prince of the Streets"
    ]
  },
  {
    "name": "Kaouther Ben Hania",
    "country": "TN",
    "tmdb_id": 1381379,
    "profile_path": "/4tUq5FvpfdqLjQLEr4dwoGiXg7f.jpg",
    "tmdb_known_for": [
      "The Voice of Hind Rajab",
      "The Man Who Sold His Skin",
      "Four Daughters"
    ]
  },
  {
    "name": "Yousry Nasrallah",
    "country": "EG",
    "tmdb_id": 1034683,
    "profile_path": "/7C0avgisV2y6EZgeKaWHpeofHvr.jpg",
    "tmdb_known_for": [
      "Scheherazade, Tell Me a Story",
      "18 Days",
      "Alexandria Again and Forever"
    ]
  },
  {
    "name": "Nouri Bouzid",
    "country": "TN",
    "tmdb_id": 1176075,
    "profile_path": "/bR39LfzgtY9o5Yw5x1PzSzDFS54.jpg",
    "tmdb_known_for": [
      "The Good Thief",
      "Man of Ashes",
      "Bezness"
    ]
  },
  {
    "name": "Marwan Hamed",
    "country": "EG",
    "tmdb_id": 1210055,
    "profile_path": "/43tAN4l0AbIFdI61PfepzxZQlsX.jpg",
    "tmdb_known_for": [
      "The Blue Elephant",
      "The Yacoubian Building",
      "Diamond Dust"
    ]
  },
  {
    "name": "Atef Salem",
    "country": "EG",
    "tmdb_id": 578067,
    "profile_path": "/q9lmGgNSTMwHV3BG6qNxxLHmsqh.jpg",
    "tmdb_known_for": [
      "Conflict in the Nile",
      "Mother of the Bride",
      "Black Tiger"
    ]
  },
  {
    "name": "Moufida Tlatli",
    "country": "TN",
    "tmdb_id": 239321,
    "profile_path": "/yx8Gc64hruNAjgw9GDCn0NHZKvI.jpg",
    "tmdb_known_for": [
      "The Silences of the Palace",
      "The Season of Men",
      "Nadia and Sarra"
    ]
  },
  {
    "name": "Mohamed Khan",
    "country": "EG",
    "tmdb_id": 1180708,
    "profile_path": "/oSqzVnOpXFXByT7u1quMVxSeXlW.jpg",
    "tmdb_known_for": [
      "The Wife of an Important Man",
      "Factory Girl",
      "The Street Player"
    ]
  },
  {
    "name": "Amr Salama",
    "country": "EG",
    "tmdb_id": 1033786,
    "profile_path": "/4mZnUMRObqnmEsycpvq1jyfBJIT.jpg",
    "tmdb_known_for": [
      "Paranormal",
      "Asmaa",
      "Sheikh Jackson"
    ]
  },
  {
    "name": "Ahmed Abdalla",
    "country": "EG",
    "tmdb_id": 4585395,
    "profile_path": null,
    "tmdb_known_for": [
      "Europa"
    ]
  }
]